Metadata-Version: 2.1
Name: funboost-install
Version: 17.4
Summary: pip install funboost，python全功能分布式函数调度框架,。支持python所有类型的并发模式和一切知名消息队列中间件，python函数加速器，框架包罗万象，一统编程思维，兼容50% python业务场景，适用范围广。只需要一行代码即可分布式执行python一切函数。旧名字是function_scheduling_distributed_framework
Home-page: https://github.com/ydf0509/funboost
Author: bfzs
Author-email: ydf0509@sohu.com
Maintainer: dragons96
Maintainer-email: 521274311@qq.com
License: BSD License
Keywords: funboost,distributed-framework,function-scheduling,rabbitmq,rocketmq,kafka,nsq,redis,disk,sqlachemy,consume-confirm,timing,task-scheduling,apscheduler,pulsar,mqtt,kombu,的,celery,框架,分布式调度
Platform: all
Classifier: Development Status :: 4 - Beta
Classifier: Operating System :: OS Independent
Classifier: Intended Audience :: Developers
Classifier: License :: OSI Approved :: BSD License
Classifier: Programming Language :: Python
Classifier: Programming Language :: Python :: Implementation
Classifier: Programming Language :: Python :: 3.6
Classifier: Programming Language :: Python :: 3.7
Classifier: Programming Language :: Python :: 3.8
Classifier: Programming Language :: Python :: 3.9
Classifier: Topic :: Software Development :: Libraries
License-File: LICENSE
Requires-Dist: nb-log (>=7.6)
Requires-Dist: pytz (>=2022.5)
Requires-Dist: apscheduler (>=3.9.1)
Requires-Dist: deprecated (>=1.2.13)
Provides-Extra: concurrent_all
Requires-Dist: eventlet (==0.31.0) ; extra == 'concurrent_all'
Requires-Dist: gevent (==21.12.0) ; extra == 'concurrent_all'
Requires-Dist: aiohttp (==3.8.0) ; extra == 'concurrent_all'
Provides-Extra: confluent_kafka
Requires-Dist: confluent-kafka (==1.7.0) ; extra == 'confluent_kafka'
Provides-Extra: debugger
Requires-Dist: pysnooper ; extra == 'debugger'
Provides-Extra: decorator
Requires-Dist: decorator (==4.4.0) ; extra == 'decorator'
Provides-Extra: eventlet
Requires-Dist: eventlet ; extra == 'eventlet'
Provides-Extra: flask_all
Requires-Dist: Flask ; extra == 'flask_all'
Requires-Dist: flask-bootstrap ; extra == 'flask_all'
Requires-Dist: flask-wtf ; extra == 'flask_all'
Requires-Dist: flask-login ; extra == 'flask_all'
Requires-Dist: wtforms ; extra == 'flask_all'
Provides-Extra: http
Requires-Dist: aiohttp (==3.8.0) ; extra == 'http'
Provides-Extra: kafka
Requires-Dist: kafka-python (==2.0.2) ; extra == 'kafka'
Provides-Extra: kafka_confluent
Requires-Dist: confluent-kafka (==1.7.0) ; extra == 'kafka_confluent'
Provides-Extra: kombu
Requires-Dist: kombu (==4.6.11) ; extra == 'kombu'
Requires-Dist: redis ; extra == 'kombu'
Provides-Extra: mongomq
Requires-Dist: pymongo (==4.0.2) ; extra == 'mongomq'
Provides-Extra: mqtt
Requires-Dist: paho-mqtt ; extra == 'mqtt'
Provides-Extra: nats
Requires-Dist: nats-python ; extra == 'nats'
Provides-Extra: nsq
Requires-Dist: gnsq (==1.0.1) ; extra == 'nsq'
Provides-Extra: peewee
Requires-Dist: peewee ; extra == 'peewee'
Requires-Dist: pymysql ; extra == 'peewee'
Provides-Extra: persistqueue
Requires-Dist: persist-queue (==0.8.0) ; extra == 'persistqueue'
Provides-Extra: playhouse
Requires-Dist: playhouse ; extra == 'playhouse'
Provides-Extra: rabbitmq_amqpstorm
Requires-Dist: amqpstorm (==2.7.1) ; extra == 'rabbitmq_amqpstorm'
Provides-Extra: rabbitmq_pika
Requires-Dist: pikav0 ; extra == 'rabbitmq_pika'
Requires-Dist: pikav1 ; extra == 'rabbitmq_pika'
Provides-Extra: rabbitmq_rabbitpy
Requires-Dist: rabbitpy (==2.0.1) ; extra == 'rabbitmq_rabbitpy'
Provides-Extra: redis
Requires-Dist: redis2 ; extra == 'redis'
Requires-Dist: redis3 ; extra == 'redis'
Provides-Extra: redis_ack_able
Requires-Dist: redis2 ; extra == 'redis_ack_able'
Requires-Dist: redis3 ; extra == 'redis_ack_able'
Provides-Extra: redis_pubsub
Requires-Dist: redis2 ; extra == 'redis_pubsub'
Requires-Dist: redis3 ; extra == 'redis_pubsub'
Provides-Extra: redis_stream
Requires-Dist: redis2 ; extra == 'redis_stream'
Requires-Dist: redis3 ; extra == 'redis_stream'
Provides-Extra: rocketmq
Requires-Dist: rocketmq ; extra == 'rocketmq'
Provides-Extra: redisbrpoplpush
Requires-Dist: redis2 ; extra == 'redisbrpoplpush'
Requires-Dist: redis3 ; extra == 'redisbrpoplpush'
Provides-Extra: sqlachemy
Requires-Dist: sqlalchemy (==1.3.10) ; extra == 'sqlachemy'
Provides-Extra: sqlite_queue
Requires-Dist: persist-queue (==0.8.0) ; extra == 'sqlite_queue'
Provides-Extra: ssh_all
Requires-Dist: fabric2 (==2.6.0) ; extra == 'ssh_all'
Requires-Dist: paramiko ; extra == 'ssh_all'
Provides-Extra: txt_file
Requires-Dist: persist-queue (==0.8.0) ; extra == 'txt_file'
Provides-Extra: zeromq
Requires-Dist: zmq ; extra == 'zeromq'
